data_explorer/__getter.py
data_explorer/__init__.py
data_explorer_by_mmd-0.1.0.dist-info/METADATA
data_explorer_by_mmd-0.1.0.dist-info/WHEEL
data_explorer_by_mmd-0.1.0.dist-info/top_level.txt
data_explorer_by_mmd-0.1.0.dist-info/RECORD
