Metadata-Version: 2.4
Name: data_explorer_by_MMD
Version: 0.1.0
Summary: Package pour explorer les données économiques de la Banque Mondiale
Author-email: Mamadou Moustapha DIALLO <mmdialloisidk1@groupeisi.com>
License: MIT
Requires-Python: >=3.7
Requires-Dist: pandas
Requires-Dist: requests
